aiden_pycounts/__init__.py
aiden_pycounts/aiden_pycounts.py
aiden_pycounts/plotting.py
aiden_pycounts-0.1.0.dist-info/LICENSE
aiden_pycounts-0.1.0.dist-info/METADATA
aiden_pycounts-0.1.0.dist-info/WHEEL
aiden_pycounts-0.1.0.dist-info/RECORD
